polyconf/core/__init__.py
polyconf/core/deepmerge.py
polyconf/core/model/__init__.py
polyconf/core/model/context.py
polyconf/core/model/datum.py
polyconf/core/model/plugin.py
polyconf/core/model/status.py
polyconf/core/registry.py
polyconf/core/typing_.py
polyconf/core/utils.py
polyconf/mock_plugins/ipsum/__init__.py
polyconf/mock_plugins/ipsum/plugin.py
polyconf/mock_plugins/lorem/__init__.py
polyconf/mock_plugins/lorem/plugin.py
polyconf-0.2.0.dist-info/LICENSE
polyconf-0.2.0.dist-info/METADATA
polyconf-0.2.0.dist-info/WHEEL
polyconf-0.2.0.dist-info/RECORD
