Metadata-Version: 2.1
Name: polyconf
Version: 0.2.0
Summary: Gather and merge configuration from many sources.
Home-page: https://polyconf.readthedocs.io
License: MIT
Keywords: polyconf,configuration
Author: Jesse Butcher
Author-email: boweeb@gmail.com
Requires-Python: >=3.11,<4.0
Classifier: Development Status :: 3 - Alpha
Classifier: Intended Audience :: Developers
Classifier: License :: OSI Approved :: MIT License
Classifier: Programming Language :: Python :: 3
Classifier: Programming Language :: Python :: 3.11
Project-URL: Documentation, https://polyconf.readthedocs.io
Project-URL: Repository, https://github.com/boweeb/polyconf
